wavepack/__init__.py
wavepack/wavelet_packet.py
wavepack-0.2.0.dist-info/LICENSE
wavepack-0.2.0.dist-info/METADATA
wavepack-0.2.0.dist-info/WHEEL
wavepack-0.2.0.dist-info/top_level.txt
wavepack-0.2.0.dist-info/RECORD
