Metadata-Version: 2.2
Name: wavepack
Version: 0.2.0
Summary: Simple differentiable ND wavelet packet decomposition in PyTorch
Author-email: "Samuel W. Remedios" <sam.remedios@gmail.com>
License:                     GNU GENERAL PUBLIC LICENSE
Project-URL: Source, https://github.com/sremedios/wavepack
Keywords: wavelet packet,wavelet tree
Classifier: Development Status :: 4 - Beta
Classifier: Programming Language :: Python :: 3
Classifier: License :: OSI Approved :: GNU General Public License v3 (GPLv3)
Classifier: Operating System :: OS Independent
Requires-Python: >=3.10
License-File: LICENSE
Requires-Dist: PyWavelets
Requires-Dist: torch
Requires-Dist: numpy
